debobo/__init__.py
debobo/detection.py
debobo/retrieval.py
debobo/utils.py
debobo/adapters/__init__.py
debobo/adapters/ignite.py
debobo-0.1.2.dist-info/LICENSE
debobo-0.1.2.dist-info/METADATA
debobo-0.1.2.dist-info/WHEEL
debobo-0.1.2.dist-info/top_level.txt
debobo-0.1.2.dist-info/RECORD
