Metadata-Version: 2.1
Name: debobo
Version: 0.1.2
Summary: Package for evaluating object detection models
Home-page: https://github.com/dseuss/debobo.git
Author: Daniel Suess
Author-email: daniel@dsuess.me
License: UNKNOWN
Platform: UNKNOWN
Classifier: Programming Language :: Python :: 3
Classifier: License :: OSI Approved :: GNU Lesser General Public License v3 (LGPLv3)
Classifier: Operating System :: OS Independent
Requires-Dist: numpy (>=1.12)
